{
  "immediateReplace": true,
  "suggester": true,
  "historyPriority": true,
  "historyLimit": 100,
  "history": [
    ":school:",
    ":link:",
    ":up:",
    ":arrow_upper_right:",
    ":point_right:",
    ":eyes:",
    ":bulb:",
    ":house:",
    ":world_map:",
    ":book:",
    ":clapper:",
    ":rocket:",
    ":file_folder:",
    ":house_with_garden:",
    ":thumbsup:",
    ":pushpin:",
    ":arrow_down_small:",
    ":notebook_with_decorative_cover:",
    ":athletic_shoe:",
    ":information_source:",
    ":green_book:",
    ":fearful:",
    ":exclamation:",
    ":warning:",
    ":smile:"
  ]
}